setup.py
ai_demos/__init__.py
ai_demos/allenai.py
ai_demos/argumentext.py
ai_demos/cogcomp.py
ai_demos/cornell.py
ai_demos/deepai.py
ai_demos/deepface.py
ai_demos/deepmoji.py
ai_demos/deepwarp.py
ai_demos/haystackai.py
ai_demos/huggingface.py
ai_demos/lrp.py
ai_demos/polyglot.py
ai_demos/pornstarbyface.py
ai_demos/semanticparsing.py
ai_demos/sense2vec.py
ai_demos/sequel.py
ai_demos/spacy.py
ai_demos/textgain.py
ai_demos/turknlp.py
ai_demos.egg-info/PKG-INFO
ai_demos.egg-info/SOURCES.txt
ai_demos.egg-info/dependency_links.txt
ai_demos.egg-info/top_level.txt