Metadata-Version: 1.0
Name: ai-demos
Version: 0.1.2
Summary: unofficial api to machine learning demos
Home-page: https://github.com/JarbasAl/ai_demos
Author: jarbasAI
Author-email: jarbasai@mailfence.com
License: MIT
Platform: UNKNOWN
